[
  {
    "n": 0,
    "i1": 0,
    "i2": 232,
    "t1": 1765263078,
    "t2": 1765274732,
    "d": 3,
    "uid": 0,
    "mrk": 0,
    "c": [
      "HIELERA-FRIGOLOGISTICA",
      "",
      "",
      {
        "t": "09.12.2025 06:51:18",
        "v": 1765263078,
        "y": -2.14202333333,
        "x": -79.7672355556,
        "u": 600463098
      },
      {
        "t": "09.12.2025 10:05:32",
        "v": 1765274732,
        "y": -2.14491166667,
        "x": -79.76904,
        "u": 600463098
      },
      "",
      "2.00 km",
      "0.18 gal",
      "11.22 km/gal"
    ],
    "r": [
      {
        "n": 0,
        "i1": 0,
        "i2": 232,
        "t1": 1765263078,
        "t2": 1765274732,
        "d": 0,
        "uid": 600463098,
        "mrk": 0,
        "c": [
          "09.12.2025 06:51:18",
          "PM089",
          "HIELERA-FRIGOLOGISTICA",
          {
            "t": "09.12.2025 06:51:18",
            "v": 1765263078,
            "y": -2.14202333333,
            "x": -79.7672355556,
            "u": 600463098
          },
          {
            "t": "09.12.2025 10:05:32",
            "v": 1765274732,
            "y": -2.14491166667,
            "x": -79.76904,
            "u": 600463098
          },
          "E49, San Jacinto De Yaguachi, Guayas, Ecuador",
          "0.71 km",
          "0.07 gal",
          "10.00 km/gal"
        ]
      },
      {
        "n": 1,
        "i1": 1,
        "i2": 122,
        "t1": 1765263156,
        "t2": 1765272529,
        "d": 0,
        "uid": 600463078,
        "mrk": 0,
        "c": [
          "09.12.2025 06:52:36",
          "PM039",
          "HIELERA-FRIGOLOGISTICA",
          {
            "t": "09.12.2025 06:52:36",
            "v": 1765263156,
            "y": -2.14216,
            "x": -79.7673777778,
            "u": 600463078
          },
          {
            "t": "09.12.2025 09:28:49",
            "v": 1765272529,
            "y": -2.14500333333,
            "x": -79.7689777778,
            "u": 600463078
          },
          "E49, San Jacinto De Yaguachi, Guayas, Ecuador",
          "0.70 km",
          "0.05 gal",
          "12.81 km/gal"
        ]
      },
      {
        "n": 2,
        "i1": 1,
        "i2": 75,
        "t1": 1765263184,
        "t2": 1765268395,
        "d": 0,
        "uid": 600463170,
        "mrk": 0,
        "c": [
          "09.12.2025 06:53:04",
          "PM085",
          "HIELERA-FRIGOLOGISTICA",
          {
            "t": "09.12.2025 06:53:04",
            "v": 1765263184,
            "y": -2.142085,
            "x": -79.7673511111,
            "u": 600463170
          },
          {
            "t": "09.12.2025 08:19:55",
            "v": 1765268395,
            "y": -2.14426333333,
            "x": -79.7691733333,
            "u": 600463170
          },
          "E49, San Jacinto De Yaguachi, Guayas, Ecuador",
          "0.59 km",
          "0.05 gal",
          "11.22 km/gal"
        ]
      }
    ],
    "tipoReporte": "3",
    "tipoReporteName": "PROHIBICIONES"
  },
  {
    "n": 1,
    "i1": 0,
    "i2": 210,
    "t1": 1765263084,
    "t2": 1765276180,
    "d": 1,
    "uid": 0,
    "mrk": 0,
    "c": [
      "HIELERA-LOG-ECUATORIANA",
      "",
      "",
      {
        "t": "09.12.2025 06:51:24",
        "v": 1765263084,
        "y": -2.29384666667,
        "x": -80.2041955555,
        "u": 600463147
      },
      {
        "t": "09.12.2025 10:29:40",
        "v": 1765276180,
        "y": -2.29187222222,
        "x": -80.2043644445,
        "u": 600463147
      },
      "",
      "0.42 km",
      "0.03 gal",
      "13.13 km/gal"
    ],
    "r": [
      {
        "n": 0,
        "i1": 0,
        "i2": 210,
        "t1": 1765263084,
        "t2": 1765276180,
        "d": 0,
        "uid": 600463147,
        "mrk": 0,
        "c": [
          "09.12.2025 06:51:24",
          "PM054",
          "HIELERA-LOG-ECUATORIANA",
          {
            "t": "09.12.2025 06:51:24",
            "v": 1765263084,
            "y": -2.29384666667,
            "x": -80.2041955555,
            "u": 600463147
          },
          {
            "t": "09.12.2025 10:29:40",
            "v": 1765276180,
            "y": -2.29187222222,
            "x": -80.2043644445,
            "u": 600463147
          },
          "E40, Guayaquil, Guayas, Ecuador",
          "0.42 km",
          "0.03 gal",
          "13.13 km/gal"
        ]
      }
    ],
    "tipoReporte": "3",
    "tipoReporteName": "PROHIBICIONES"
  }
]